MANIFEST.in
requirements.txt
setup.cfg
setup.py
napalm_junos/__init__.py
napalm_junos/constants.py
napalm_junos/junos.py
napalm_junos.egg-info/PKG-INFO
napalm_junos.egg-info/SOURCES.txt
napalm_junos.egg-info/dependency_links.txt
napalm_junos.egg-info/requires.txt
napalm_junos.egg-info/top_level.txt
napalm_junos/templates/delete_ntp_peers.j2
napalm_junos/templates/delete_ntp_servers.j2
napalm_junos/templates/delete_probes.j2
napalm_junos/templates/delete_snmp_config.j2
napalm_junos/templates/delete_users.j2
napalm_junos/templates/schedule_probes.j2
napalm_junos/templates/set_hostname.j2
napalm_junos/templates/set_ntp_peers.j2
napalm_junos/templates/set_ntp_servers.j2
napalm_junos/templates/set_probes.j2
napalm_junos/templates/set_users.j2
napalm_junos/templates/snmp_config.j2
napalm_junos/utils/__init__.py
napalm_junos/utils/junos_views.py
napalm_junos/utils/junos_views.yml