Metadata-Version: 1.1
Name: napalm-junos
Version: 0.10.1
Summary: Network Automation and Programmability Abstraction Layer with Multivendor support
Home-page: https://github.com/napalm-automation/napalm-junos
Author: David Barroso, Mircea Ulinic
Author-email: dbarrosop@dravetech.com, mircea@cloudflare.com
License: UNKNOWN
Platform: UNKNOWN
Classifier: Topic :: Utilities
Classifier: Programming Language :: Python
Classifier: Operating System :: POSIX :: Linux
Classifier: Operating System :: MacOS
